kanglib/__init__.py
kanglib/calculations.py
kanglib-0.5.dist-info/METADATA
kanglib-0.5.dist-info/WHEEL
kanglib-0.5.dist-info/top_level.txt
kanglib-0.5.dist-info/RECORD
