Metadata-Version: 2.1
Name: kanglib
Version: 0.5
Summary: Kang lib of Python package: calculate my math function
Home-page: https://github.com/williampolicy/code_pypi
Author: xiaowen kang
Author-email: kangxiaowen@gmail.com
License: MIT
